LICENSE.txt
MANIFEST.in
README.md
pyproject.toml
setup.py
libsecp256k1/CHANGELOG.md
libsecp256k1/CMakeLists.txt
libsecp256k1/CMakePresets.json
libsecp256k1/CONTRIBUTING.md
libsecp256k1/COPYING
libsecp256k1/Makefile.am
libsecp256k1/README.md
libsecp256k1/SECURITY.md
libsecp256k1/autogen.sh
libsecp256k1/configure.ac
libsecp256k1/libsecp256k1.pc.in
libsecp256k1/build-aux/m4/bitcoin_secp.m4
libsecp256k1/cmake/CheckArm32Assembly.cmake
libsecp256k1/cmake/CheckMemorySanitizer.cmake
libsecp256k1/cmake/CheckStringOptionValue.cmake
libsecp256k1/cmake/CheckX86_64Assembly.cmake
libsecp256k1/cmake/FindValgrind.cmake
libsecp256k1/cmake/GeneratePkgConfigFile.cmake
libsecp256k1/cmake/TryAppendCFlags.cmake
libsecp256k1/cmake/arm-linux-gnueabihf.toolchain.cmake
libsecp256k1/cmake/config.cmake.in
libsecp256k1/cmake/source_arm32.s
libsecp256k1/cmake/x86_64-w64-mingw32.toolchain.cmake
libsecp256k1/contrib/lax_der_parsing.c
libsecp256k1/contrib/lax_der_parsing.h
libsecp256k1/contrib/lax_der_privatekey_parsing.c
libsecp256k1/contrib/lax_der_privatekey_parsing.h
libsecp256k1/doc/ellswift.md
libsecp256k1/doc/musig.md
libsecp256k1/doc/release-process.md
libsecp256k1/doc/safegcd_implementation.md
libsecp256k1/examples/CMakeLists.txt
libsecp256k1/examples/EXAMPLES_COPYING
libsecp256k1/examples/ecdh.c
libsecp256k1/examples/ecdsa.c
libsecp256k1/examples/ellswift.c
libsecp256k1/examples/examples_util.h
libsecp256k1/examples/musig.c
libsecp256k1/examples/schnorr.c
libsecp256k1/include/secp256k1.h
libsecp256k1/include/secp256k1_ecdh.h
libsecp256k1/include/secp256k1_ellswift.h
libsecp256k1/include/secp256k1_extrakeys.h
libsecp256k1/include/secp256k1_musig.h
libsecp256k1/include/secp256k1_preallocated.h
libsecp256k1/include/secp256k1_recovery.h
libsecp256k1/include/secp256k1_schnorrsig.h
libsecp256k1/sage/gen_exhaustive_groups.sage
libsecp256k1/sage/gen_split_lambda_constants.sage
libsecp256k1/sage/group_prover.sage
libsecp256k1/sage/prove_group_implementations.sage
src/electrum_ecc.egg-info/PKG-INFO
src/electrum_ecc.egg-info/SOURCES.txt
src/electrum_ecc.egg-info/dependency_links.txt
src/electrum_ecc.egg-info/top_level.txt
