Metadata-Version: 2.4
Name: electrum-ecc
Version: 0.0.5
Summary: Pure python ctypes wrapper for libsecp256k1
Author: The Electrum developers
License: MIT License
Project-URL: Homepage, https://github.com/spesmilo/electrum-ecc
Project-URL: Repository, https://github.com/spesmilo/electrum-ecc
Keywords: libsecp256k1,ecc
Classifier: Development Status :: 4 - Beta
Classifier: Intended Audience :: Developers
Classifier: License :: OSI Approved :: MIT License
Classifier: Natural Language :: English
Classifier: Operating System :: OS Independent
Classifier: Programming Language :: Python :: 3
Classifier: Programming Language :: Python :: 3.8
Classifier: Programming Language :: Python :: 3.9
Classifier: Programming Language :: Python :: 3.10
Classifier: Programming Language :: Python :: 3.11
Classifier: Programming Language :: Python :: 3.12
Classifier: Programming Language :: Python :: Implementation :: CPython
Classifier: Topic :: Software Development :: Libraries
Classifier: Topic :: Security :: Cryptography
Requires-Python: >=3.8
License-File: LICENSE.txt
Dynamic: license-file
